ts_features_sculptor/.coverage
ts_features_sculptor/__init__.py
ts_features_sculptor/_version.py
ts_features_sculptor/__pycache__/__init__.cpython-312.pyc
ts_features_sculptor/generators/event_generator.py
ts_features_sculptor/generators/flexible_cyclical_generator.py
ts_features_sculptor/generators/individual_inactivity_generator.py
ts_features_sculptor/generators/structured_cyclical_generator.py
ts_features_sculptor/generators/temporal_generator.py
ts_features_sculptor/generators/__pycache__/__init__.cpython-312.pyc
ts_features_sculptor/generators/__pycache__/event_generator.cpython-312.pyc
ts_features_sculptor/generators/__pycache__/flexible_cyclical_generator.cpython-312.pyc
ts_features_sculptor/generators/__pycache__/individual_inactivity_generator.cpython-312.pyc
ts_features_sculptor/generators/__pycache__/structured_cyclical_generator.cpython-312.pyc
ts_features_sculptor/generators/__pycache__/temporal_generator.cpython-312.pyc
ts_features_sculptor/transformers/__init__.py
ts_features_sculptor/transformers/active_to_inactive.py
ts_features_sculptor/transformers/activity_range_classifier.py
ts_features_sculptor/transformers/calendar_assignment_policy_stats.py
ts_features_sculptor/transformers/cooldown_eligibility.py
ts_features_sculptor/transformers/date_time_decomposer.py
ts_features_sculptor/transformers/days_of_life.py
ts_features_sculptor/transformers/days_since_last_event.py
ts_features_sculptor/transformers/episode_splitter.py
ts_features_sculptor/transformers/event_counters.py
ts_features_sculptor/transformers/event_counters_postproc.py
ts_features_sculptor/transformers/event_days_features.py
ts_features_sculptor/transformers/event_driven_ts_compressor.py
ts_features_sculptor/transformers/ewm_smoother.py
ts_features_sculptor/transformers/flagged_events_expanding_stats.py
ts_features_sculptor/transformers/future_window_target.py
ts_features_sculptor/transformers/group_aggregate.py
ts_features_sculptor/transformers/group_daily_lag.py
ts_features_sculptor-1.23.0.dist-info/licenses/LICENSE
ts_features_sculptor-1.23.0.dist-info/METADATA
ts_features_sculptor-1.23.0.dist-info/WHEEL
ts_features_sculptor-1.23.0.dist-info/top_level.txt
ts_features_sculptor-1.23.0.dist-info/RECORD
