Metadata-Version: 2.4
Name: ts_features_sculptor
Version: 1.23.0
Summary: Package for transforming time series features
Author-email: "Nikolskii D.N." <nikolskydn@mail.ru>
License: MIT
Project-URL: Homepage, https://github.com/nikolskydn/ts_features_sculptor
Classifier: Programming Language :: Python :: 3
Classifier: License :: OSI Approved :: MIT License
Classifier: Operating System :: OS Independent
Requires-Python: >=3.10
License-File: LICENSE
Requires-Dist: pandas>=2.2.3
Requires-Dist: scikit-learn>=1.5.1
Requires-Dist: holidays>=0.31
Requires-Dist: numpy>=1.24.0
Provides-Extra: dev
Requires-Dist: pytest>=7.4.0; extra == "dev"
Requires-Dist: pytest-cov>=4.1.0; extra == "dev"
Requires-Dist: build>=1.0.3; extra == "dev"
Requires-Dist: twine>=4.0.2; extra == "dev"
Requires-Dist: black>=23.12.0; extra == "dev"
Requires-Dist: isort>=5.13.2; extra == "dev"
Requires-Dist: flake8>=6.1.0; extra == "dev"
Dynamic: license-file
